python_env_resolver/__init__.py
python_env_resolver/audit.py
python_env_resolver/constants.py
python_env_resolver/py.typed
python_env_resolver/resolver.py
python_env_resolver/resolvers.py
python_env_resolver/types.py
python_env_resolver/utils.py
python_env_resolver/validators.py
python_env_resolver-2.0.0.dist-info/METADATA
python_env_resolver-2.0.0.dist-info/WHEEL
python_env_resolver-2.0.0.dist-info/licenses/LICENSE
python_env_resolver-2.0.0.dist-info/RECORD
