Metadata-Version: 2.4
Name: python-env-resolver
Version: 2.0.0
Summary: Type-safe environment variable handling for Python with Pydantic
Project-URL: Homepage, https://github.com/jagreehal/python-env-resolver
Project-URL: Documentation, https://github.com/jagreehal/python-env-resolver#readme
Project-URL: Repository, https://github.com/jagreehal/python-env-resolver
Project-URL: Issues, https://github.com/jagreehal/python-env-resolver/issues
Project-URL: Changelog, https://github.com/jagreehal/python-env-resolver/releases
Author-email: Jag Reehal <jag@jagreehal.com>
License: MIT
License-File: LICENSE
Keywords: config,configuration,dotenv,env,environment,pydantic,secrets,settings,validation
Classifier: Development Status :: 4 - Beta
Classifier: Intended Audience :: Developers
Classifier: License :: OSI Approved :: MIT License
Classifier: Programming Language :: Python :: 3
Classifier: Programming Language :: Python :: 3.10
Classifier: Programming Language :: Python :: 3.11
Classifier: Programming Language :: Python :: 3.12
Classifier: Programming Language :: Python :: 3.13
Classifier: Topic :: Software Development :: Libraries :: Python Modules
Classifier: Topic :: System :: Systems Administration
Classifier: Typing :: Typed
Requires-Python: >=3.10
Requires-Dist: pydantic>=2.0
Requires-Dist: pydantic[email]>=2.12.0
Requires-Dist: python-dotenv>=1.0.0
Provides-Extra: aws
Requires-Dist: boto3>=1.34; extra == 'aws'
Provides-Extra: dev
Requires-Dist: mypy>=1.8.0; extra == 'dev'
Requires-Dist: pytest-asyncio>=0.23.0; extra == 'dev'
Requires-Dist: pytest>=8.0; extra == 'dev'
Requires-Dist: ruff>=0.4.0; extra == 'dev'
Provides-Extra: http
Requires-Dist: httpx>=0.27; extra == 'http'
